flask_oauthlib/__init__.py
flask_oauthlib/client.py
flask_oauthlib/utils.py
flask_oauthlib/contrib/__init__.py
flask_oauthlib/contrib/apps.py
flask_oauthlib/contrib/cache.py
flask_oauthlib/contrib/oauth2.py
flask_oauthlib/contrib/client/__init__.py
flask_oauthlib/contrib/client/application.py
flask_oauthlib/contrib/client/descriptor.py
flask_oauthlib/contrib/client/exceptions.py
flask_oauthlib/contrib/client/signals.py
flask_oauthlib/contrib/client/structure.py
flask_oauthlib/provider/__init__.py
flask_oauthlib/provider/oauth1.py
flask_oauthlib/provider/oauth2.py
Flask_OAuthlib_Invenio-1.1.2.dist-info/AUTHORS
Flask_OAuthlib_Invenio-1.1.2.dist-info/LICENSE
Flask_OAuthlib_Invenio-1.1.2.dist-info/METADATA
Flask_OAuthlib_Invenio-1.1.2.dist-info/WHEEL
Flask_OAuthlib_Invenio-1.1.2.dist-info/top_level.txt
Flask_OAuthlib_Invenio-1.1.2.dist-info/RECORD
