Metadata-Version: 2.2
Name: Flask-OAuthlib-Invenio
Version: 1.1.2
Summary: OAuthlib for Flask.
Home-page: https://github.com/inveniosoftware/flask-oauthlib-invenio
Author: CERN/TU Graz
Author-email: info@inveniosoftware.org
License: BSD
Keywords: flask OAuth2
Platform: any
Classifier: Development Status :: 5 - Production/Stable
Requires-Python: >=3.9
License-File: LICENSE
License-File: AUTHORS
Requires-Dist: Flask>=3.0
Requires-Dist: cachelib>=0.9.0
Requires-Dist: oauthlib>=3.0.0
Requires-Dist: requests-oauthlib>=1.0
Provides-Extra: tests
Requires-Dist: pytest-black-ng>=0.4.0; extra == "tests"
Requires-Dist: pytest-invenio<4.0.0,>=3.0.0; extra == "tests"
Requires-Dist: mock>=5.1.0; extra == "tests"
